linkml_model_enrichment/annotators/curated_to_enums.py
linkml_model_enrichment/annotators/enum_annotator.py
linkml_model_enrichment/annotators/enums_to_curateable.py
linkml_model_enrichment/annotators/schema_annotator.py
linkml_model_enrichment/dosdp/dosdp_linkml.yaml
linkml_model_enrichment/dosdp/model.py
linkml_model_enrichment/importers/csv_import_engine.py
linkml_model_enrichment/importers/dosdp_import_engine.py
linkml_model_enrichment/importers/import_engine.py
linkml_model_enrichment/importers/infer_model_from_rdftab.py
linkml_model_enrichment/importers/json_instance_import_engine.py
linkml_model_enrichment/importers/jsonschema_import_engine.py
linkml_model_enrichment/importers/owl_import_engine.py
linkml_model_enrichment/importers/rdf_instance_import_engine.py
linkml_model_enrichment/jsonschema/jsonschema.py
linkml_model_enrichment/utils/enums_pvs_tsv.py
linkml_model_enrichment/utils/schemautils.py
linkml_model_enrichment-0.0.5.dist-info/entry_points.txt
linkml_model_enrichment-0.0.5.dist-info/LICENSE
linkml_model_enrichment-0.0.5.dist-info/WHEEL
linkml_model_enrichment-0.0.5.dist-info/METADATA
linkml_model_enrichment-0.0.5.dist-info/RECORD
